yescieval/VERSION
yescieval/__init__.py
yescieval/base/__init__.py
yescieval/base/domain.py
yescieval/base/judge.py
yescieval/base/parser.py
yescieval/base/rubric.py
yescieval/injector/__init__.py
yescieval/injector/domains/__init__.py
yescieval/injector/domains/ecology.py
yescieval/injector/domains/nlp.py
yescieval/injector/example.py
yescieval/injector/vocab.py
yescieval/judge/__init__.py
yescieval/judge/custom.py
yescieval/judge/judges.py
yescieval/parser/__init__.py
yescieval/parser/parsers.py
yescieval/rubric/__init__.py
yescieval/rubric/breadth.py
yescieval/rubric/depth.py
yescieval/rubric/fidelity.py
yescieval/rubric/gap.py
yescieval/rubric/innovation.py
yescieval/rubric/rigor.py
yescieval/rubric/structural.py
yescieval/rubric/stylistic.py
yescieval-0.5.0.dist-info/METADATA
yescieval-0.5.0.dist-info/WHEEL
yescieval-0.5.0.dist-info/licenses/LICENSE
yescieval-0.5.0.dist-info/RECORD
