Metadata-Version: 2.4
Name: YESciEval
Version: 0.5.0
Summary: YESciEval: Robust LLM-as-a-Judge for Scientific Question Answering.
License: MIT
License-File: LICENSE
Author: Hamed Babaei Giglou
Author-email: hamedbabaeigiglou@gmail.com
Requires-Python: >=3.10,<4.0.0
Classifier: License :: OSI Approved :: MIT License
Classifier: Programming Language :: Python :: 3
Classifier: Programming Language :: Python :: 3.10
Classifier: Programming Language :: Python :: 3.11
Classifier: Programming Language :: Python :: 3.12
Classifier: Programming Language :: Python :: 3.13
Classifier: Programming Language :: Python :: 3.14
Requires-Dist: numpy
Requires-Dist: openai
Requires-Dist: pandas
Requires-Dist: peft
Requires-Dist: pre-commit
Requires-Dist: pydantic
Requires-Dist: torch
Requires-Dist: transformers
Project-URL: Homepage, https://yescieval.readthedocs.io/
Project-URL: Repository, https://github.com/sciknoworg/YESciEval/
